i18n/__init__.py
i18n/formatter.py
i18n/i18n.py
i18n/py.typed
i18n_lib-0.2.0.dist-info/METADATA
i18n_lib-0.2.0.dist-info/WHEEL
i18n_lib-0.2.0.dist-info/licenses/LICENSE
i18n_lib-0.2.0.dist-info/RECORD
