Metadata-Version: 2.4
Name: i18n-lib
Version: 0.2.0
Summary: i18n lib
Project-URL: Homepage, https://github.com/HamletSargsyan/i18n-lib
Project-URL: Documentation, https://hamletsargsyan.github.io/i18n-lib/usage
Author-email: Hamlet <hamlets849@gmail.com>
License-Expression: MIT
License-File: LICENSE
Keywords: i18n,internationalization,localization
Classifier: Development Status :: 4 - Beta
Classifier: Intended Audience :: Developers
Classifier: License :: OSI Approved :: MIT License
Classifier: Operating System :: OS Independent
Classifier: Programming Language :: Python
Classifier: Programming Language :: Python :: 3
Classifier: Programming Language :: Python :: 3.9
Classifier: Programming Language :: Python :: 3.10
Classifier: Programming Language :: Python :: 3.11
Classifier: Programming Language :: Python :: 3.13
Classifier: Programming Language :: Python :: Implementation :: CPython
Classifier: Topic :: Software Development :: Internationalization
Classifier: Topic :: Software Development :: Localization
Classifier: Typing :: Typed
Requires-Python: >=3.9
Requires-Dist: pyyaml>=6.0.2
